{
  "car": [
    "Car",
    "Truck",
    "Convertible",
    "Tire",
    "Engine",
    "Steering wheel",
    "Horn",
    "Gas station",
    "Accident",
    "License plate",
    "Blinker",
    "Clutch",
    "Rearview mirror",
    "Wipers",
    "GPS",
    "Trunk",
    "Ignition key",
    "Gas pedal",
    "Brake",
    "Handbrake",
    "Trailer",
    "Garage",
    "MOT",
    "Traffic light",
    "Car wash",
    "Cruise control",
    "Overtake",
    "Parking spot",
    "Bodywork",
    "Bumper",
    "Hood",
    "Chassis",
    "Transmission",
    "Seatbelt",
    "Airbag",
    "Driving instructor",
    "Highway",
    "Dashboard",
    "Electric car",
    "Hybrid",
    "License",
    "Speed limit",
    "Fuel",
    "Maintenance",
    "Driving test",
    "Rental car",
    "Backseat",
    "Wheel",
    "Mirror",
    "Dashboard camera"
  ],
  "sport": [
    "Soccer",
    "Tennis",
    "Basketball",
    "Swimming",
    "Running",
    "Gymnastics",
    "Boxing",
    "Cycling",
    "Climbing",
    "Skiing",
    "Snowboarding",
    "Ice hockey",
    "Baseball",
    "Rugby",
    "Horse riding",
    "Golf",
    "Surfing",
    "Fencing",
    "Judo",
    "Karate",
    "Handball",
    "Marathon",
    "Sprint",
    "Diving",
    "Shooting",
    "Fishing",
    "Bowling",
    "Skateboarding",
    "Yoga",
    "Sailing",
    "Canoeing",
    "Triathlon",
    "Bouldering",
    "Snowkiting",
    "Darts",
    "Motorsport",
    "Wrestling",
    "Skating",
    "Slackline",
    "Parkour",
    "Archery",
    "Pole vault",
    "High jump",
    "Long jump",
    "Ping pong",
    "Snooker",
    "Rollerblading",
    "Hiking",
    "Obstacle race",
    "Ice skating"
  ],
  "geography": [
    "Continent",
    "Island",
    "River",
    "Mountain range",
    "City",
    "Country",
    "Capital",
    "Ocean",
    "Desert",
    "Lake",
    "Forest",
    "Valley",
    "Volcano",
    "Border",
    "Compass",
    "Latitude",
    "Longitude",
    "Glacier",
    "Peninsula",
    "Map",
    "Globe",
    "Fjord",
    "National park",
    "Meadow",
    "Coast",
    "Cliff",
    "Cave",
    "Steppe",
    "Wave",
    "Geography",
    "Province",
    "Region",
    "Atoll",
    "Area",
    "Tundra",
    "Savannah",
    "Population",
    "Climate zone",
    "World map",
    "Shore",
    "Delta",
    "Rainforest",
    "Hill",
    "Bay",
    "Archipelago",
    "Territory",
    "Timezone",
    "Plateau",
    "Plain",
    "Landmark"
  ],
  "film": [
    "Action",
    "Comedy",
    "Drama",
    "Thriller",
    "Horror",
    "Camera",
    "Director",
    "Script",
    "Cinema",
    "Blockbuster",
    "Scene",
    "Actor",
    "Premiere",
    "Film reel",
    "Location",
    "Trailer",
    "Prop",
    "Costume",
    "Extra",
    "Voice actor",
    "Popcorn",
    "Lighting",
    "Sound",
    "Stunt",
    "Casting",
    "Trilogy",
    "Credits",
    "Oscar",
    "Soundtrack",
    "Direction",
    "Assistant director",
    "Producer",
    "Review",
    "Screening",
    "Animation",
    "Documentary",
    "Romance",
    "Audience",
    "Film festival",
    "Streaming",
    "Streaming service",
    "Award",
    "Short film",
    "Indie film",
    "Set",
    "Dialogue",
    "Plot",
    "Narrator",
    "Genre",
    "Sequel"
  ],
  "animal": [
    "Dog",
    "Cat",
    "Elephant",
    "Tiger",
    "Bear",
    "Monkey",
    "Lion",
    "Mouse",
    "Horse",
    "Zebra",
    "Snake",
    "Bird",
    "Penguin",
    "Kangaroo",
    "Giraffe",
    "Fox",
    "Rabbit",
    "Cow",
    "Pig",
    "Sheep",
    "Fish",
    "Shark",
    "Whale",
    "Octopus",
    "Crab",
    "Owl",
    "Frog",
    "Crocodile",
    "Hedgehog",
    "Peacock",
    "Badger",
    "Lynx",
    "Eagle",
    "Crane",
    "Panther",
    "Koala",
    "Puma",
    "Stork",
    "Bee",
    "Beetle",
    "Goat",
    "Rooster",
    "Swan",
    "Seal",
    "Wolf",
    "Camel",
    "Donkey",
    "Moose",
    "Deer",
    "Parrot"
  ],
  "jobs": [
    "Teacher",
    "Doctor",
    "Engineer",
    "Chef",
    "Lawyer",
    "Hairdresser",
    "Police officer",
    "Firefighter",
    "Pilot",
    "Farmer",
    "Salesperson",
    "Mechanic",
    "Artist",
    "Musician",
    "Architect",
    "Designer",
    "Journalist",
    "Baker",
    "Bricklayer",
    "Dentist",
    "Photographer",
    "Veterinarian",
    "Actor",
    "Taxi driver",
    "Electrician",
    "Plumber",
    "Tailor",
    "Educator",
    "Chemist",
    "Programmer",
    "Broker",
    "Judge",
    "Notary",
    "Interpreter",
    "Surgeon",
    "Florist",
    "Painter",
    "Psychologist",
    "Scientist",
    "Nurse",
    "Cashier",
    "Consultant",
    "Receptionist",
    "Driver",
    "Analyst",
    "Barista",
    "Waiter",
    "Trainer",
    "Butcher",
    "Cleaner"
  ],
  "stars": [
    "Cristiano Ronaldo",
    "Heidi Klum",
    "Elon Musk",
    "Kim Kardashian",
    "Leonardo DiCaprio",
    "Justin Bieber",
    "Selena Gomez",
    "Taylor Swift",
    "Lionel Messi",
    "Angelina Jolie",
    "Brad Pitt",
    "Shakira",
    "Tom Cruise",
    "Beyoncé",
    "Ariana Grande",
    "Kanye West",
    "Oprah Winfrey",
    "Ed Sheeran",
    "Dwayne Johnson",
    "Jennifer Lopez",
    "Harry Styles",
    "Zendaya",
    "Billie Eilish",
    "Rihanna",
    "Drake",
    "Emma Watson",
    "Shawn Mendes",
    "Lady Gaga",
    "George Clooney",
    "Will Smith",
    "Pedro Pascal",
    "Robert Downey Jr.",
    "Chris Hemsworth",
    "Zac Efron",
    "Margot Robbie",
    "Florence Pugh",
    "Timothée Chalamet",
    "Miley Cyrus",
    "Kylie Jenner",
    "Doja Cat",
    "Post Malone",
    "Olivia Rodrigo",
    "Cardi B",
    "Snoop Dogg",
    "Kendall Jenner",
    "Gigi Hadid",
    "Tom Holland",
    "Adele",
    "Lizzo",
    "Gordon Ramsay"
  ],
  "drugs": [
    "Aspirin",
    "Penicillin",
    "Insulin",
    "Ibuprofen",
    "Morphine",
    "Antibiotic",
    "Paracetamol",
    "Caffeine",
    "Alcohol",
    "Nicotine",
    "Cannabis",
    "Cocaine",
    "LSD",
    "Ecstasy",
    "Heroin",
    "Pill",
    "Injection",
    "Patch",
    "Medication",
    "Side effect",
    "Dosage",
    "Prescription",
    "Doctor",
    "Pharmacy",
    "Doping",
    "Tranquilizer",
    "Painkiller",
    "Addiction",
    "Dependence",
    "Withdrawal",
    "Active ingredient",
    "Suppository",
    "Homeopathy",
    "High",
    "Overdose",
    "Therapy",
    "Pharmacy",
    "Leaflet",
    "Interaction",
    "Placebo",
    "Tablet",
    "Antidepressant",
    "Antihistamine",
    "Syringe",
    "Inhaler",
    "Capsule",
    "Substance",
    "Drugstore",
    "Cure",
    "Treatment"
  ],
  "music": [
    "Rock",
    "Pop",
    "Jazz",
    "Classical",
    "HipHop",
    "Guitar",
    "Piano",
    "Drums",
    "Singer",
    "Song",
    "Concert",
    "Beat",
    "Melody",
    "Rhythm",
    "Notes",
    "Choir",
    "Band",
    "Tone",
    "Voice",
    "Microphone",
    "Headphones",
    "Speaker",
    "Radio",
    "DJ",
    "Album",
    "Single",
    "Composer",
    "Conductor",
    "Opera",
    "Festival",
    "Streaming",
    "Vinyl",
    "Cover",
    "Remix",
    "Playlist",
    "Stage",
    "Duet",
    "Auditorium",
    "Lyrics",
    "Hit",
    "Bass",
    "Synthesizer",
    "Genre",
    "Record",
    "Grammy",
    "Studio",
    "Tour",
    "Encore",
    "Chorus",
    "Bridge"
  ],
  "party": [
    "Dance",
    "Music",
    "DJ",
    "Speaker",
    "Balloon",
    "Cake",
    "Gift",
    "Candles",
    "Invitation",
    "Champagne",
    "Fairy lights",
    "Snacks",
    "Buffet",
    "Beer pong",
    "Mood",
    "Guests",
    "Costume",
    "Theme",
    "Fireworks",
    "Midnight",
    "Confetti",
    "Conga line",
    "Limbo",
    "Karaoke",
    "Birthday",
    "Farewell",
    "Flirt",
    "Selfie",
    "Hangover",
    "Photo booth",
    "Liquor",
    "Shots",
    "Disco",
    "Dancefloor",
    "DJ booth",
    "New Year's",
    "Celebration",
    "Drink",
    "Strobe",
    "Toast",
    "Party hat",
    "Invitation card",
    "Glow stick",
    "Afterparty",
    "Decoration",
    "Loud music",
    "Noisemaker",
    "Surprise",
    "Cocktail",
    "Friends"
  ],
  "series": [
    "Friends",
    "Breaking Bad",
    "Game of Thrones",
    "Stranger Things",
    "Money Heist",
    "The Witcher",
    "Sherlock",
    "The Office",
    "How I Met Your Mother",
    "Vikings",
    "Loki",
    "Wednesday",
    "The Mandalorian",
    "Better Call Saul",
    "Dark",
    "Lost",
    "Dexter",
    "Narcos",
    "Brooklyn Nine-Nine",
    "Modern Family",
    "The Big Bang Theory",
    "Peaky Blinders",
    "Squid Game",
    "Lucifer",
    "The Crown",
    "The Boys",
    "Black Mirror",
    "Arrow",
    "Suits",
    "You",
    "The 100",
    "Euphoria",
    "House of the Dragon",
    "Emily in Paris",
    "Riverdale",
    "The Good Doctor",
    "Elite",
    "This Is Us",
    "Grey’s Anatomy",
    "Sex Education",
    "The Last of Us",
    "Ozark",
    "The Umbrella Academy",
    "Manifest",
    "13 Reasons Why",
    "New Girl",
    "Mindhunter",
    "The Queen’s Gambit",
    "Severance",
    "Fargo"
  ]
}
